LICENSE.txt
MANIFEST.in
README.rst
setup.cfg
setup.py
data/data_file
data/kkk_file
kkk/__init__.py
kkk/kkk.txt
kkk/package_data.dat
kkk.egg-info/PKG-INFO
kkk.egg-info/SOURCES.txt
kkk.egg-info/dependency_links.txt
kkk.egg-info/entry_points.txt
kkk.egg-info/requires.txt
kkk.egg-info/top_level.txt