Metadata-Version: 1.1
Name: kkk
Version: 0.0.2
Summary: My kids are cuter than yours
Home-page: https://github.com/lucyking/pypi-project-kkk
Author: lucyking
Author-email: joehisaishi1943@gmail.com
License: GPL
Keywords: auto setup RFUI env
Platform: UNKNOWN
Classifier: Development Status :: 3 - Alpha
Classifier: Intended Audience :: Developers
Classifier: Topic :: Software Development :: Build Tools
Classifier: License :: OSI Approved :: MIT License
Classifier: Programming Language :: Python :: 2
Classifier: Programming Language :: Python :: 2.6
Classifier: Programming Language :: Python :: 2.7
Classifier: Programming Language :: Python :: 3
Classifier: Programming Language :: Python :: 3.2
Classifier: Programming Language :: Python :: 3.3
Classifier: Programming Language :: Python :: 3.4
Classifier: Programming Language :: Python :: 3.5
